gryszkapackage/__init__.py
gryszkapackage/hello_file.py
gryszkapackage-0.1.1.dist-info/LICENSE
gryszkapackage-0.1.1.dist-info/METADATA
gryszkapackage-0.1.1.dist-info/WHEEL
gryszkapackage-0.1.1.dist-info/top_level.txt
gryszkapackage-0.1.1.dist-info/RECORD
